autoxplainai/__init__.py
autoxplainai/explainer.py
autoxplainai/utils.py
autoxplainai/visualization.py
tests/__init__.py
tests/test_explainer.py
tests/test_visualization.py
AutoXplainAI-0.2.0.dist-info/METADATA
AutoXplainAI-0.2.0.dist-info/WHEEL
AutoXplainAI-0.2.0.dist-info/top_level.txt
AutoXplainAI-0.2.0.dist-info/RECORD
