Metadata-Version: 2.2
Name: AutoXplainAI
Version: 0.2.0
Summary: An Automatic Model Explanation Framework
Home-page: https://github.com/gopalakrishnanarjun/AutoXplainAI.git
Author: Gopalakrishnan Arjunan
Author-email: gopalakrishnana02@gmail.com
Classifier: Programming Language :: Python :: 3
Classifier: License :: OSI Approved :: MIT License
Classifier: Operating System :: OS Independent
Requires-Python: >=3.7
Requires-Dist: numpy
Requires-Dist: pandas
Requires-Dist: matplotlib
Requires-Dist: scikit-learn
Requires-Dist: shap
Dynamic: author
Dynamic: author-email
Dynamic: classifier
Dynamic: description
Dynamic: description-content-type
Dynamic: home-page
Dynamic: requires-dist
Dynamic: requires-python
Dynamic: summary
